<annotation>
  <folder>resistor</folder>
  <filename>res227.jpeg</filename>
  <segmented>0</segmented>
  <size>
    <width>774</width>
    <height>251</height>
    <depth>3</depth>
  </size>
  <object>
    <name>resistor</name>
    <pose>Unspecified</pose>
    <truncated>0</truncated>
    <difficult>0</difficult>
    <bndbox>
      <xmin>380</xmin>
      <ymin>16</ymin>
      <xmax>567</xmax>
      <ymax>85</ymax>
    </bndbox>
  </object>
  <object>
    <name>resistor</name>
    <pose>Unspecified</pose>
    <truncated>0</truncated>
    <difficult>0</difficult>
    <bndbox>
      <xmin>127</xmin>
      <ymin>18</ymin>
      <xmax>317</xmax>
      <ymax>91</ymax>
    </bndbox>
  </object>
  <object>
    <name>resistor</name>
    <pose>Unspecified</pose>
    <truncated>0</truncated>
    <difficult>0</difficult>
    <bndbox>
      <xmin>631</xmin>
      <ymin>8</ymin>
      <xmax>773</xmax>
      <ymax>94</ymax>
    </bndbox>
  </object>
</annotation>
