<annotation>
  <folder>resistor</folder>
  <filename>res523.jpeg</filename>
  <segmented>0</segmented>
  <size>
    <width>226</width>
    <height>437</height>
    <depth>3</depth>
  </size>
  <object>
    <name>resistor</name>
    <pose>Unspecified</pose>
    <truncated>0</truncated>
    <difficult>0</difficult>
    <bndbox>
      <xmin>143</xmin>
      <ymin>31</ymin>
      <xmax>204</xmax>
      <ymax>145</ymax>
    </bndbox>
  </object>
  <object>
    <name>resistor</name>
    <pose>Unspecified</pose>
    <truncated>0</truncated>
    <difficult>0</difficult>
    <bndbox>
      <xmin>43</xmin>
      <ymin>93</ymin>
      <xmax>85</xmax>
      <ymax>165</ymax>
    </bndbox>
  </object>
  <object>
    <name>resistor</name>
    <pose>Unspecified</pose>
    <truncated>0</truncated>
    <difficult>0</difficult>
    <bndbox>
      <xmin>81</xmin>
      <ymin>302</ymin>
      <xmax>138</xmax>
      <ymax>410</ymax>
    </bndbox>
  </object>
</annotation>
